{"cameraMode":{"drawMode":0,"name":"Shaded","section":"Shading Mode"},"sceneLighting":false,"audioPlay":false,"sceneViewState":{"showFog":true,"showMaterialUpdate":false,"showSkybox":false,"showFlares":true,"showImageEffects":true,"showParticleSystems":true},"in2DMode":false,"pivot":{"x":-0.2759703993797302,"y":0.2129291445016861,"z":-0.0768909826874733},"rotation":{"x":0.16741149127483369,"y":0.5614842772483826,"z":-0.1172342374920845,"w":0.801974356174469},"size":0.708872377872467,"orthographic":false}